{"meta": {"symptom": [{"name": "Bloody or red colored vomit", "id": 36}], "bodypart": {"name": "Upper Abdomen", "id": 22}}, "status": "ok", "code": 1, "data": {"conditions": [{"chronid": "091e9c5e80007c17", "ccui": "C0017181", "weight": 11.8, "tid": 4276, "conchronid": "091e9c5e808e7b36", "name": "Gastrointestinal bleeding", "sev": 5, "curl": "http://www.emedicinehealth.com/gastrointestinal_bleeding/article_em.htm", "id": 356, "lev": 5}, {"chronid": "091e9c5e8001e1cf", "ccui": "C0030920", "weight": 2.8, "tid": 4093, "conchronid": "091e9c5e808e7c4d", "name": "Peptic ulcer", "sev": 0, "curl": "http://www.webmd.com/hw/digestive_problems/hw217849.asp", "id": 183, "lev": 3}, {"chronid": "091e9c5e80007c17", "ccui": "C0155789", "weight": 2.0, "tid": 4291, "conchronid": "091e9c5e808e7bc0", "name": "Bleeding esophageal varices", "sev": 0, "curl": "http://www.emedicinehealth.com/gastrointestinal_bleeding/article_em.htm", "id": 854, "lev": 3}, {"chronid": "091e9c5e800c5b69", "ccui": "C0017160", "weight": 2.0, "tid": 4276, "conchronid": "091e9c5e808e7ba6", "name": "Gastroenteritis", "sev": 0, "curl": "http://www.emedicinehealth.com/gastroenteritis/article_em.htm", "id": 355, "lev": 3}, {"chronid": "091e9c5e8001ee22", "ccui": "C0024633", "weight": 2.0, "tid": 4116, "conchronid": "091e9c5e808e7b9c", "name": "Mallory-Weiss syndrome", "sev": 0, "curl": "http://www.webmd.com/hw/digestive_problems/nord734.asp", "id": 853, "lev": 3}, {"chronid": "091e9c5e8001dd5d", "ccui": "C0374997", "weight": 1.4, "tid": 4093, "conchronid": "091e9c5e808e7b89", "name": "Helicobacter pylori infection", "sev": 0, "curl": "http://www.webmd.com/hw/digestive_problems/hw217863.asp", "id": 360, "lev": 2}, {"chronid": "091e9c5e8001e27c", "ccui": "C0006370", "weight": 1.0, "tid": 7006, "conchronid": "091e9c5e808e7b0c", "name": "Bulimia", "sev": 0, "curl": "http://www.webmd.com/hw/health_guide_atoz/hw49747.asp", "id": 529, "lev": 1}, {"chronid": "091e9c5e800f3e73", "ccui": "C0546837", "weight": 1.0, "tid": 2946, "conchronid": "091e9c5e808e7af5", "name": "Esophageal cancer", "sev": 0, "curl": "http://www.webmd.com/hw/cancer/ncicdr0000062960-general-information-about-esophageal-cancer.asp", "id": 87, "lev": 1}, {"chronid": "091e9c5e80008a8c", "ccui": "C0014867", "weight": 1.0, "tid": 4291, "conchronid": "091e9c5e808e7adf", "name": "Esophageal varices", "sev": 0, "curl": "http://www.webmd.com/content/article/90/100613.htm", "id": 1059, "lev": 1}, {"chronid": "091e9c5e80007c3b", "ccui": "C0014868", "weight": 1.0, "tid": 4276, "conchronid": "091e9c5e808e7c79", "name": "Esophagitis", "sev": 0, "curl": "http://www.webmd.com/content/article/90/100654.htm", "id": 613, "lev": 1}, {"chronid": "091e9c5e8000b22c", "ccui": "C0412842", "weight": 1.0, "tid": 6032, "conchronid": "091e9c5e808e7b55", "name": "Iron poisoning", "sev": 5, "curl": "http://www.emedicinehealth.com/iron_poisoning/article_em.htm", "id": 376, "lev": 1}, {"chronid": "091e9c5e8001d2c7", "ccui": "C0859942", "weight": 1.0, "tid": 4291, "conchronid": "091e9c5e808e7b84", "name": "Primary biliary cirrhosis", "sev": 0, "curl": "http://www.webmd.com/hw/digestive_problems/tp21140.asp", "id": 860, "lev": 1}, {"chronid": "091e9c5e8001e4cf", "ccui": "C0520753", "weight": 1.0, "tid": 4276, "conchronid": "091e9c5e808e7bfe", "name": "Swallowed object", "sev": 0, "curl": "http://www.emedicinehealth.com/swallowed_object/article_em.htm", "id": 674, "lev": 1}, {"chronid": "091e9c5e8001eee9", "ccui": "C0004763", "weight": 0.6, "tid": 4093, "conchronid": "091e9c5e808e80d9", "name": "Barrett esophagus", "sev": 0, "curl": "http://www.webmd.com/hw/heartburn/nord173.asp", "id": 735, "lev": 1}, {"chronid": "091e9c5e800079b8", "ccui": "C0153424", "weight": 0.5, "tid": 2946, "conchronid": "091e9c5e808e81c9", "name": "Stomach cancer", "sev": 0, "curl": "http://www.emedicinehealth.com/stomach_cancer/article_em.htm", "id": 672, "lev": 1}]}}