{"meta": {"symptom": [{"name": "Swelling", "id": 5}], "bodypart": {"name": "Eye", "id": 3}}, "status": "ok", "code": 1, "data": {"conditions": [{"chronid": "091e9c5e8001dcdf", "ccui": "C0149512", "weight": 2.0, "tid": 4286, "conchronid": "091e9c5e808e7c45", "name": "Acute sinusitis", "sev": 0, "curl": "http://www.webmd.com/hw/infection/hw67421.asp", "id": 9, "lev": 5}, {"chronid": "091e9c5e8001e7cd", "ccui": "C1527304", "weight": 2.0, "tid": 1625, "conchronid": "091e9c5e808e7bc5", "name": "Allergic reaction", "sev": 0, "curl": "http://www.emedicinehealth.com/allergic_reaction/article_em.htm", "id": 478, "lev": 5}, {"chronid": "091e9c5e8001d191", "ccui": "C0018621", "weight": 2.0, "tid": 1625, "conchronid": "091e9c5e808e7ae0", "name": "Hay fever", "sev": 0, "curl": "http://www.webmd.com/hw/allergies/hw33438.asp", "id": 115, "lev": 5}, {"chronid": "091e9c5e8000ae5e", "ccui": "C0009763", "weight": 2.0, "tid": 4286, "conchronid": "091e9c5e808e8113", "name": "Pink eye (conjunctivitis)", "sev": 0, "curl": "http://www.emedicinehealth.com/pinkeye/article_em.htm", "id": 188, "lev": 5}, {"chronid": "091e9c5e802123f3", "ccui": "C1274548", "weight": 1.0, "tid": 6032, "conchronid": "091e9c5e808e7c69", "name": "Bee or wasp stings", "sev": 0, "curl": "http://www.emedicinehealth.com/bee_and_wasp_stings/article_em.htm", "id": 500, "lev": 3}, {"chronid": "091e9c5e8000ae93", "ccui": "C0009766", "weight": 1.0, "tid": 1625, "conchronid": "091e9c5e808e81d0", "name": "Eye allergies", "sev": 0, "curl": "http://www.emedicinehealth.com/eye_allergies/article_em.htm", "id": 691, "lev": 3}, {"chronid": "091e9c5e8001e645", "ccui": "C0375246", "weight": 1.0, "tid": 6032, "conchronid": "091e9c5e808e8080", "name": "Foreign object in the eye", "sev": 0, "curl": "http://www.emedicinehealth.com/foreign_body_eye/article_em.htm", "id": 95, "lev": 3}, {"chronid": "091e9c5e8001e72b", "ccui": "C0021564", "weight": 1.0, "tid": 6032, "conchronid": "091e9c5e808e7b65", "name": "Insect bites", "sev": 0, "curl": "http://www.emedicinehealth.com/insect_bites/article_em.htm", "id": 373, "lev": 3}, {"chronid": "091e9c5e8001d2b3", "ccui": "C0079626", "weight": 1.0, "tid": 4116, "conchronid": "091e9c5e808e7bfb", "name": "Insect sting", "sev": 0, "curl": "http://www.webmd.com/hw/skin_wounds/tp22238.asp", "id": 374, "lev": 3}, {"chronid": "091e9c5e8001d94e", "ccui": "C0032342", "weight": 1.0, "tid": 1625, "conchronid": "091e9c5e808e7cad", "name": "Poison ivy, oak, and sumac", "sev": 0, "curl": "http://www.webmd.com/hw/allergies/hw75041.asp", "id": 196, "lev": 3}, {"chronid": "091e9c5e8001e483", "ccui": "C0701836", "weight": 0.6, "tid": 6032, "conchronid": "091e9c5e808e7bb0", "name": "Burn (heat or fire)", "sev": 0, "curl": "http://www.emedicinehealth.com/thermal_heat_or_fire_burns/article_em.htm", "id": 677, "lev": 2}, {"chronid": "091e9c5e80010a27", "ccui": "C0006435", "weight": 0.6, "tid": 6032, "conchronid": "091e9c5e808e80d7", "name": "Chemical burns", "sev": 5, "curl": "http://www.emedicinehealth.com/chemical_burns/article_em.htm", "id": 535, "lev": 2}]}}