{"meta": {"symptom": [{"name": "Muscle cramps or spasms (painful)", "id": 282}], "bodypart": {"name": "Arm", "id": 40}}, "status": "ok", "code": 1, "data": {"conditions": [{"chronid": "091e9c5e8001e22a", "ccui": "C0026769", "weight": 1.0, "tid": 1827, "conchronid": "091e9c5e808e7b95", "name": "Multiple sclerosis", "sev": 0, "curl": "http://www.webmd.com/hw/multiple_sclerosis/hw190816.asp", "id": 395, "lev": 5}, {"chronid": "091e9c5e8001ee7a", "ccui": "C0039621", "weight": 1.0, "tid": 3073, "conchronid": "091e9c5e808e7ade", "name": "Tetany", "sev": 5, "curl": "http://www.webmd.com/hw/hormonal_disorders/nord703.asp", "id": 451, "lev": 5}, {"chronid": "091e9c5e8001ef14", "ccui": "C0041234", "weight": 0.5, "tid": 4286, "conchronid": "091e9c5e808e7c7a", "name": "Chagas disease", "sev": 0, "curl": "http://www.webmd.com/hw/infection/nord147.asp", "id": 713, "lev": 3}, {"chronid": "091e9c5e8001d572", "ccui": "C0085209", "weight": 0.5, "tid": 4286, "conchronid": "091e9c5e808e7aa3", "name": "Mad cow disease", "sev": 0, "curl": "http://www.emedicinehealth.com/mad_cow_disease_and_variant_creutzfeldt-jakob_dis/article_em.htm", "id": 387, "lev": 3}, {"chronid": "091e9c5e8001eff2", "ccui": "C0033806", "weight": 0.5, "tid": 4284, "conchronid": "091e9c5e808e8099", "name": "Pseudohypoparathyroidism", "sev": 0, "curl": "http://www.webmd.com/hw/hormonal_disorders/nord625.asp", "id": 798, "lev": 3}, {"chronid": "091e9c5e80de3543", "ccui": "C0017921", "weight": 0.0, "tid": 3609, "conchronid": "091e9c5e80de3543", "name": "Pompe disease (late-onset)", "sev": 0, "curl": "", "id": 1220, "lev": 1}]}}