{"meta": {"symptom": [{"name": "Dizziness", "id": 81}], "bodypart": {"name": "General", "id": 66}}, "status": "ok", "code": 1, "data": {"conditions": [{"chronid": "091e9c5e8001ddc9", "ccui": "C0025281", "weight": 1.0, "tid": 4116, "conchronid": "091e9c5e808e80ea", "name": "Meniere's disease", "sev": 0, "curl": "http://www.webmd.com/hw/balance_disorders/hw220240.asp", "id": 158, "lev": 5}, {"chronid": "091e9c5e8001ac80", "ccui": "C0026603", "weight": 1.0, "tid": 3073, "conchronid": "091e9c5e808e7c2c", "name": "Motion sickness", "sev": 0, "curl": "http://www.webmd.com/hw/ear_disorders/uf4438.asp", "id": 816, "lev": 5}]}}